{
    "AARTIDRUGS": "Aarti Drugs Limited",
    "AARTIIND": "Aarti Industries Limited",
    "AMARAJABAT": "Amara Raja Batteries Limited",
    "EICHERMOT": "Eicher Motors Limited",
    "EXIDEIND": "Exide Industries Limited",
    "INFY": "Infosys Limited",
    "RELIANCE": "Reliance Industries Limited",
    "RPOWER": "Reliance Power Limited",
    "TCS": "Tata Consultancy Services Limited",
    "VINATIORGA": "Vinati Organics Limited",
    "XPROINDIA": "Xpro India Limited",
    "ZOMATO": "Zomato Limited"
}